[{"id": 1, "nombre": "punto de encuentro", "direccion": "calle Paraguay y Colombia", "precio": "15$", "lng": "-79.19889450073244", "lat": "-3.999513626364509"},{"id": 2, "nombre": "sintetica Podocarpus", "direccion": "parque Podocarpus", "precio": "12$", "lng": "-79.20181274414064", "lat": "-3.9974587039471476"},{"id": 3, "nombre": "calva y calva", "direccion": "av. pio jaramillo", "precio": "20$", "lng": "-79.20370101928712", "lat": "-3.9974587039471476"},{"id": 4, "nombre": "Jogo Bonito", "direccion": "calle Bernardo Valdivieso", "precio": "17$", "lng": "-79.19940412044527", "lat": "-4.009398586760957"}]